graylog_lib/__init__.py
graylog_lib/graylog_http_gelf.py
gray_py_gelf-1.2.0.dist-info/LICENSE
gray_py_gelf-1.2.0.dist-info/METADATA
gray_py_gelf-1.2.0.dist-info/WHEEL
gray_py_gelf-1.2.0.dist-info/top_level.txt
gray_py_gelf-1.2.0.dist-info/RECORD
