Metadata-Version: 2.1
Name: gray-py-gelf
Version: 1.2.0
Summary: This project aims to simplify log shipping to your graylog server quite simply
Home-page: https://github.com/rafaelsanches123/GraylogHttpGelfPython
Author: Rafael Francisco Viana Sanches
Author-email: rafaelsanches123@gmail.com
License: UNKNOWN
Keywords: graylog,python3.6,json,api,rafael sanches
Platform: UNKNOWN
Classifier: Programming Language :: Python :: 3.6
Classifier: License :: OSI Approved :: MIT License
Classifier: Operating System :: OS Independent
Requires-Python: >=3.6
Requires-Dist: requests
